pypugjs/__init__.py
pypugjs/compiler.py
pypugjs/convert.py
pypugjs/exceptions.py
pypugjs/filters.py
pypugjs/lexer.py
pypugjs/nodes.py
pypugjs/parser.py
pypugjs/runtime.py
pypugjs/utils.py
pypugjs/ext/__init__.py
pypugjs/ext/html.py
pypugjs/ext/jinja.py
pypugjs/ext/mako.py
pypugjs/ext/underscore.py
pypugjs/ext/django/__init__.py
pypugjs/ext/django/compiler.py
pypugjs/ext/django/loader.py
pypugjs/ext/django/templatetags.py
pypugjs/ext/pyramid/__init__.py
pypugjs/ext/tornado/__init__.py
pypugjs-5.12.0.dist-info/LICENSE
pypugjs-5.12.0.dist-info/METADATA
pypugjs-5.12.0.dist-info/WHEEL
pypugjs-5.12.0.dist-info/entry_points.txt
pypugjs-5.12.0.dist-info/top_level.txt
pypugjs-5.12.0.dist-info/RECORD
