Metadata-Version: 2.1
Name: pypugjs
Version: 5.12.0
Summary: PugJS syntax template adapter for Django, Jinja2, Mako and Tornado templates
Home-page: https://github.com/kakulukia/pypugjs
Download-URL: https://github.com/kakulukia/pypugjs/tarball/5.12.0
Author: Andy Grabow
Author-email: andy@freilandkiwis.de
License: MIT
Keywords: pug,pugjs,template,converter
Classifier: Development Status :: 5 - Production/Stable
Classifier: Intended Audience :: Developers
Classifier: License :: OSI Approved :: MIT License
Classifier: Operating System :: OS Independent
Classifier: Programming Language :: Python
Classifier: Natural Language :: English
Classifier: Programming Language :: Python :: 3
Classifier: Programming Language :: Python :: 3.4
Classifier: Programming Language :: Python :: 3.5
Classifier: Programming Language :: Python :: 3.6
Classifier: Programming Language :: Python :: 3.7
Classifier: Programming Language :: Python :: 3.8
Classifier: Programming Language :: Python :: 3.9
Classifier: Programming Language :: Python :: 3.10
Classifier: Framework :: Django
Classifier: Framework :: Django :: 1.11
Classifier: Framework :: Django :: 2.0
Classifier: Framework :: Django :: 3.0
Classifier: Framework :: Django :: 4.0
Classifier: Topic :: Software Development :: Libraries :: Python Modules
License-File: LICENSE
Requires-Dist: six
Requires-Dist: charset_normalizer
